pypi_browser/__init__.py
pypi_browser/app.py
pypi_browser/packaging.py
pypi_browser/pypi.py
pypi_browser/static/bootstrap-5.2.1.min.css
pypi_browser/static/bootstrap-5.2.1.min.js
pypi_browser/static/favicon.png
pypi_browser/static/site.css
pypi_browser/static/site.js
pypi_browser/templates/_base.html
pypi_browser/templates/_macros.html
pypi_browser/templates/home.html
pypi_browser/templates/package.html
pypi_browser/templates/package_file.html
pypi_browser/templates/package_file_archive_path.html
pypi_browser_webapp-0.0.12.dist-info/METADATA
pypi_browser_webapp-0.0.12.dist-info/WHEEL
pypi_browser_webapp-0.0.12.dist-info/RECORD
