Metadata-Version: 2.1
Name: pypi-browser-webapp
Version: 0.0.12
Summary: PyPI package browsing web application
License: Apache-2.0
Author: Chris Kuehl
Author-email: ckuehl@ckuehl.me
Requires-Python: >=3.10,<4.0
Classifier: License :: OSI Approved :: Apache Software License
Classifier: Programming Language :: Python :: 3
Classifier: Programming Language :: Python :: 3.10
Classifier: Programming Language :: Python :: 3.11
Classifier: Programming Language :: Python :: 3.12
Requires-Dist: Jinja2
Requires-Dist: MarkupSafe
Requires-Dist: Pygments
Requires-Dist: aiofiles
Requires-Dist: fluffy-code
Requires-Dist: httpx
Requires-Dist: identify
Requires-Dist: packaging
Requires-Dist: starlette
